<?xml version="1.0"?>
<Interface Version="1" Minor="1">
	<Ifc Id="ROOT" Top="1">
		<Bus Id="SA">
			<Port Id="3" Dir="OUT"/>
			<Port Id="2" Dir="OUT"/>
			<Port Id="1" Dir="OUT"/>
			<Port Id="0" Dir="OUT"/>
		</Bus>
		<Bus Id="LED">
			<Port Id="7" Dir="OUT"/>
			<Port Id="6" Dir="OUT"/>
			<Port Id="5" Dir="OUT"/>
			<Port Id="4" Dir="OUT"/>
			<Port Id="3" Dir="OUT"/>
			<Port Id="2" Dir="OUT"/>
			<Port Id="1" Dir="OUT"/>
			<Port Id="0" Dir="OUT"/>
		</Bus>
		<Port Id="I1" Dir="IN"/>
		<Port Id="I2" Dir="IN"/>
	</Ifc>
</Interface>

